{
	"info": {
		"_postman_id": "5510a99f-fa72-4bce-8573-04195e2d90eb",
		"name": "Amazon Clone",
		"schema": "https://schema.getpostman.com/json/collection/v2.1.0/collection.json"
	},
	"item": [
		{
			"name": "Functional",
			"item": [
				{
					"name": "Login",
					"request": {
						"method": "POST",
						"header": [],
						"url": {
							"raw": "{{hostname}}/login",
							"host": [
								"{{hostname}}"
							],
							"path": [
								"login"
							]
						}
					},
					"response": []
				},
				{
					"name": "Signup",
					"request": {
						"method": "GET",
						"header": [],
						"url": {
							"raw": "{{hostname}}/signup",
							"host": [
								"{{hostname}}"
							],
							"path": [
								"signup"
							]
						}
					},
					"response": []
				}
			],
			"protocolProfileBehavior": {}
		},
		{
			"name": "Ping",
			"request": {
				"method": "GET",
				"header": [],
				"url": {
					"raw": "{{hostname}}/ping",
					"host": [
						"{{hostname}}"
					],
					"path": [
						"ping"
					]
				}
			},
			"response": []
		}
	],
	"protocolProfileBehavior": {}
}